wwr_api/__init__.py
wwr_api/api.py
wwr_api-0.0.3.dist-info/LICENSE
wwr_api-0.0.3.dist-info/METADATA
wwr_api-0.0.3.dist-info/WHEEL
wwr_api-0.0.3.dist-info/top_level.txt
wwr_api-0.0.3.dist-info/RECORD
