Metadata-Version: 2.1
Name: wwr-api
Version: 0.0.3
Summary: WorkWechat Robot APIs
Home-page: https://github.com/Thoxvi/WorkWechat-Robot-API
Author: Thoxvi
Author-email: A@Thoxvi.com
License: UNKNOWN
Keywords: api workwechat
Platform: UNKNOWN
Requires-Python: >=3.4
Requires-Dist: requests
